Metadata-Version: 2.1
Name: hps360pen
Version: 0.1b2
Summary: hps360pen is a sample tool to map HP Spectre x360 ap00xxxx stock pen buttons
Home-page: https://github.com/GusBite/hps360pen
Author: Eric Grenier
Author-email: eric.grenier@pm.me
License: MIT LICENSE
Platform: UNKNOWN
Classifier: Development Status :: 4 - Beta
Classifier: Operating System :: POSIX :: Linux
Classifier: Programming Language :: Python :: 3 :: Only
Classifier: Programming Language :: Python :: 3.6
Classifier: Programming Language :: Python :: 3.7
Classifier: Programming Language :: Python :: 3.8
